mavlinkHandler/__init__.py
mavlinkHandler/mavlinkHandler.py
mavlinkHandler-0.0.16.dist-info/LICENSE
mavlinkHandler-0.0.16.dist-info/METADATA
mavlinkHandler-0.0.16.dist-info/WHEEL
mavlinkHandler-0.0.16.dist-info/top_level.txt
mavlinkHandler-0.0.16.dist-info/RECORD
